pip_install_privates/__init__.py
pip_install_privates/install.py
pip_install_privates/utils.py
pip_install_privates-0.5.dist-info/LICENSE
pip_install_privates-0.5.dist-info/METADATA
pip_install_privates-0.5.dist-info/WHEEL
pip_install_privates-0.5.dist-info/entry_points.txt
pip_install_privates-0.5.dist-info/top_level.txt
pip_install_privates-0.5.dist-info/RECORD
