Metadata-Version: 2.1
Name: pip-install-privates
Version: 0.5
Summary: Install pip packages from private repositories without an ssh agent
Home-page: https://github.com/ByteInternet/pip-install-privates
Author: Byte Internet
Author-email: tech@byte.nl
License: MIT
Platform: UNKNOWN
Requires-Dist: pip
